ray_simplify/__init__.py
ray_simplify/constants.py
ray_simplify/context.py
ray_simplify/core.py
ray_simplify/decorators.py
ray_simplify/exceptions.py
ray_simplify/executor.py
ray_simplify/functions.py
ray_simplify/process_manager.py
ray_simplify-1.0.0.dist-info/METADATA
ray_simplify-1.0.0.dist-info/WHEEL
ray_simplify-1.0.0.dist-info/licenses/LICENSE
ray_simplify-1.0.0.dist-info/RECORD
