Metadata-Version: 2.4
Name: ray_simplify
Version: 1.0.0
Summary: Simplify use of ray
Project-URL: Homepage, https://github.com/DINHDUY/ray_simplify
Project-URL: Documentation, https://github.com/DINHDUY/ray_simplify#readme
Project-URL: Repository, https://github.com/DINHDUY/ray_simplify.git
Project-URL: Issues, https://github.com/DINHDUY/ray_simplify/issues
Author-email: Dinhduy Tran <dinhduy.tran@live.com>
License-Expression: MIT
License-File: LICENSE
Classifier: Development Status :: 4 - Beta
Classifier: Intended Audience :: Developers
Classifier: License :: OSI Approved :: MIT License
Classifier: Operating System :: OS Independent
Classifier: Programming Language :: Python :: 3
Classifier: Programming Language :: Python :: 3.8
Classifier: Programming Language :: Python :: 3.9
Classifier: Programming Language :: Python :: 3.10
Classifier: Programming Language :: Python :: 3.11
Classifier: Programming Language :: Python :: 3.12
Requires-Python: >=3.11
Requires-Dist: ray>=2.48.0
Provides-Extra: dev
Requires-Dist: black>=23.0.0; extra == 'dev'
Requires-Dist: commitizen>=3.0.0; extra == 'dev'
Requires-Dist: pre-commit>=3.0.0; extra == 'dev'
Requires-Dist: pytest-cov>=4.0.0; extra == 'dev'
Requires-Dist: pytest>=7.0.0; extra == 'dev'
Requires-Dist: ruff>=0.1.0; extra == 'dev'
